settings_collector/__init__.py
settings_collector/collector.py
settings_collector/defaults.py
settings_collector/exceptions.py
settings_collector/manager.py
settings_collector/py.typed
settings_collector/setting.py
settings_collector/settings.py
settings_collector/test.py
settings_collector/undef.py
settings_collector/value.py
settings_collector/version.py
settings_collector/loaders/__init__.py
settings_collector/loaders/base.py
settings_collector/loaders/bottle.py
settings_collector/loaders/cherrypy.py
settings_collector/loaders/django.py
settings_collector/loaders/env.py
settings_collector/loaders/flask.py
settings_collector/loaders/make_init_imports.sh
settings_collector/loaders/pyramid.py
settings_collector/loaders/settings.py
settings_collector/loaders/turbogears.py
settings_collector-1.2.1.dist-info/METADATA
settings_collector-1.2.1.dist-info/WHEEL
settings_collector-1.2.1.dist-info/RECORD
