Metadata-Version: 2.1
Name: settings-collector
Version: 1.2.1
Summary: Package for collecting settings from various sources
Project-URL: Homepage, https://github.com/vsego/settings-collector
Project-URL: Bug Tracker, https://github.com/vsego/settings-collector/issues
Project-URL: Changelog, https://github.com/vsego/settings-collector/blob/master/CHANGELOG.md
Author-email: Vedran Sego <vsego@vsego.org>
Keywords: configuration,django,environment,flask,frameworks,packages,settings
Classifier: Development Status :: 5 - Production/Stable
Classifier: Framework :: Bottle
Classifier: Framework :: CherryPy
Classifier: Framework :: Django
Classifier: Framework :: Flask
Classifier: Framework :: Pyramid
Classifier: Framework :: TurboGears
Classifier: Intended Audience :: Developers
Classifier: Operating System :: OS Independent
Classifier: Programming Language :: Python :: 3.6
Classifier: Topic :: Software Development :: Libraries :: Python Modules
Classifier: Topic :: Utilities
Classifier: Typing :: Typed
Requires-Python: >=3.6
